dslash/__init__.py
dslash/choices.py
dslash/client.py
dslash/commands.py
dslash/groups.py
dslash/options.py
dslash/permissions.py
dslash/py.typed
dslash-0.7.2.dist-info/LICENSE
dslash-0.7.2.dist-info/METADATA
dslash-0.7.2.dist-info/WHEEL
dslash-0.7.2.dist-info/RECORD
