Metadata-Version: 2.3
Name: dslash
Version: 0.7.2
Summary: A library which supplements Nextcord by adding support for slash commands.
License: MIT
Keywords: discord,discord.py,nextcord,slash commands,extension
Author: Artemis
Author-email: me@arty.li
Requires-Python: >=3.12,<4.0
Classifier: Development Status :: 4 - Beta
Classifier: Intended Audience :: Developers
Classifier: License :: OSI Approved :: MIT License
Classifier: Operating System :: OS Independent
Classifier: Programming Language :: Python :: 3
Classifier: Programming Language :: Python :: 3.12
Classifier: Programming Language :: Python :: 3.13
Classifier: Typing :: Typed
Requires-Dist: docstring-parser (>=0.17,<0.18)
Requires-Dist: nextcord (>=3.0.0,<4.0.0)
Project-URL: Homepage, https://github.com/artemis21/dslash
Project-URL: Repository, https://github.com/artemis21/dslash
